basictdf/__init__.py
basictdf/basictdf.py
basictdf/tdfBlock.py
basictdf/tdfCalibrationData.py
basictdf/tdfData2D.py
basictdf/tdfData3D.py
basictdf/tdfEMG.py
basictdf/tdfEvents.py
basictdf/tdfForce3D.py
basictdf/tdfForcePlatformsCalibration.py
basictdf/tdfForcePlatformsData.py
basictdf/tdfOpticalSystem.py
basictdf/tdfTypes.py
basictdf/tdfUtils.py
basictdf-0.1.14.dist-info/METADATA
basictdf-0.1.14.dist-info/WHEEL
basictdf-0.1.14.dist-info/RECORD
