Metadata-Version: 2.1
Name: basictdf
Version: 0.1.14
Summary: A basic TDF parser
Author: Marcos A. Núñez
Author-email: silver94@gmail.com
Requires-Python: >=3.7,<4.0
Classifier: Programming Language :: Python :: 3
Classifier: Programming Language :: Python :: 3.7
Classifier: Programming Language :: Python :: 3.8
Classifier: Programming Language :: Python :: 3.9
Classifier: Programming Language :: Python :: 3.10
Classifier: Programming Language :: Python :: 3.11
Classifier: Programming Language :: Python :: 3.12
Requires-Dist: numpy (<=1.21) ; python_version >= "3.7" and python_version < "3.8"
Requires-Dist: numpy (>=1.22,<2.0) ; python_version >= "3.8"
